{
    "parties": [
        {
            "slug": "spd",
            "name": "SPD"
        },
        {
            "slug": "fdp",
            "name": "FDP"
        },
        {
            "slug": "union",
            "name": "Union"
        },
        {
            "slug": "gruene",
            "name": "Gr\u00fcne"
        },
        {
            "slug": "linke",
            "name": "Linke"
        },
        {
            "slug": "afd",
            "name": "AfD"
        }
    ],
    "bubbles": [
        {
            "party": "union",
            "year": 1949,
            "size": 31.01,
            "fontSize": 12,
            "x": {
                "umap": 16.052116394,
                "tsne": 100.0,
                "pca": 81.3204365794
            },
            "y": {
                "umap": 78.0548477173,
                "tsne": 59.4163703918,
                "pca": 36.276790378
            }
        },
        {
            "party": "fdp",
            "year": 1949,
            "size": 11.92,
            "fontSize": 12,
            "x": {
                "umap": 10.5090169907,
                "tsne": 95.0357131958,
                "pca": 89.5429622521
            },
            "y": {
                "umap": 70.958946228,
                "tsne": 49.391330719,
                "pca": 45.7060569136
            }
        },
        {
            "party": "linke",
            "year": 1949,
            "size": 0.0,
            "fontSize": 12,
            "x": {
                "umap": 5.8116817474,
                "tsne": 97.0085601807,
                "pca": 93.3141224803
            },
            "y": {
                "umap": 83.7694091797,
                "tsne": 78.7072372437,
                "pca": 41.627771246
            }
        },
        {
            "party": "spd",
            "year": 1949,
            "size": 29.22,
            "fontSize": 12,
            "x": {
                "umap": 0.0,
                "tsne": 97.9474334717,
                "pca": 86.6838258966
            },
            "y": {
                "umap": 76.6872787476,
                "tsne": 71.6834030151,
                "pca": 43.9911031477
            }
        },
        {
            "party": "union",
            "year": 1953,
            "size": 45.17,
            "fontSize": 12,
            "x": {
                "umap": 16.6318435669,
                "tsne": 93.9675216675,
                "pca": 86.6737016628
            },
            "y": {
                "umap": 85.1612014771,
                "tsne": 84.2308197021,
                "pca": 30.4839860782
            }
        },
        {
            "party": "fdp",
            "year": 1953,
            "size": 9.54,
            "fontSize": 12,
            "x": {
                "umap": 79.8770065308,
                "tsne": 64.2903594971,
                "pca": 89.5266865567
            },
            "y": {
                "umap": 0.0,
                "tsne": 31.1026268005,
                "pca": 40.936113825
            }
        },
        {
            "party": "spd",
            "year": 1953,
            "size": 28.84,
            "fontSize": 12,
            "x": {
                "umap": 3.8178822994,
                "tsne": 84.8614501953,
                "pca": 82.2430267601
            },
            "y": {
                "umap": 61.8012084961,
                "tsne": 49.1908149719,
                "pca": 44.7158711023
            }
        },
        {
            "party": "union",
            "year": 1957,
            "size": 50.19,
            "fontSize": 12,
            "x": {
                "umap": 17.919960022,
                "tsne": 86.9648208618,
                "pca": 100.0
            },
            "y": {
                "umap": 96.4521026611,
                "tsne": 94.4389724731,
                "pca": 33.4562810717
            }
        },
        {
            "party": "fdp",
            "year": 1957,
            "size": 7.71,
            "fontSize": 12,
            "x": {
                "umap": 27.4511508942,
                "tsne": 86.0439987183,
                "pca": 92.8979428918
            },
            "y": {
                "umap": 78.481010437,
                "tsne": 70.2922973633,
                "pca": 41.8545897403
            }
        },
        {
            "party": "spd",
            "year": 1957,
            "size": 31.75,
            "fontSize": 12,
            "x": {
                "umap": 24.9536170959,
                "tsne": 85.6108932495,
                "pca": 82.7038524852
            },
            "y": {
                "umap": 70.8720245361,
                "tsne": 68.8791351318,
                "pca": 23.7652107845
            }
        },
        {
            "party": "union",
            "year": 1961,
            "size": 45.32,
            "fontSize": 12,
            "x": {
                "umap": 22.9545288086,
                "tsne": 85.2087860107,
                "pca": 91.9859144981
            },
            "y": {
                "umap": 100.0,
                "tsne": 94.4335021973,
                "pca": 37.8044039065
            }
        },
        {
            "party": "fdp",
            "year": 1961,
            "size": 12.77,
            "fontSize": 12,
            "x": {
                "umap": 36.9023551941,
                "tsne": 84.9815826416,
                "pca": 83.6321082122
            },
            "y": {
                "umap": 73.3168106079,
                "tsne": 29.3163394928,
                "pca": 35.5716234633
            }
        },
        {
            "party": "spd",
            "year": 1961,
            "size": 36.22,
            "fontSize": 12,
            "x": {
                "umap": 15.699136734,
                "tsne": 84.9358825684,
                "pca": 84.785132075
            },
            "y": {
                "umap": 59.0741157532,
                "tsne": 57.326133728,
                "pca": 28.6666214818
            }
        },
        {
            "party": "union",
            "year": 1965,
            "size": 47.59,
            "fontSize": 12,
            "x": {
                "umap": 29.6186294556,
                "tsne": 59.2194747925,
                "pca": 79.9011692501
            },
            "y": {
                "umap": 12.9956588745,
                "tsne": 100.0,
                "pca": 9.9069400603
            }
        },
        {
            "party": "fdp",
            "year": 1965,
            "size": 9.49,
            "fontSize": 12,
            "x": {
                "umap": 5.1413660049,
                "tsne": 73.1543807983,
                "pca": 74.64688899
            },
            "y": {
                "umap": 47.1222572327,
                "tsne": 29.5036487579,
                "pca": 35.7547420524
            }
        },
        {
            "party": "spd",
            "year": 1965,
            "size": 39.28,
            "fontSize": 12,
            "x": {
                "umap": 10.9271869659,
                "tsne": 84.8854980469,
                "pca": 71.3778626846
            },
            "y": {
                "umap": 54.5291976929,
                "tsne": 42.618812561,
                "pca": 20.2976196924
            }
        },
        {
            "party": "union",
            "year": 1969,
            "size": 46.09,
            "fontSize": 12,
            "x": {
                "umap": 8.5139684677,
                "tsne": 75.4432830811,
                "pca": 73.4619031206
            },
            "y": {
                "umap": 30.6662883759,
                "tsne": 91.4902420044,
                "pca": 20.3797762169
            }
        },
        {
            "party": "fdp",
            "year": 1969,
            "size": 5.77,
            "fontSize": 12,
            "x": {
                "umap": 41.6654853821,
                "tsne": 68.9331741333,
                "pca": 68.2137982775
            },
            "y": {
                "umap": 59.9734420776,
                "tsne": 15.4865627289,
                "pca": 36.8657626437
            }
        },
        {
            "party": "spd",
            "year": 1969,
            "size": 42.67,
            "fontSize": 12,
            "x": {
                "umap": 20.5688533783,
                "tsne": 74.3446960449,
                "pca": 70.2190897033
            },
            "y": {
                "umap": 32.9950790405,
                "tsne": 58.918094635,
                "pca": 17.1706692494
            }
        },
        {
            "party": "union",
            "year": 1972,
            "size": 44.86,
            "fontSize": 12,
            "x": {
                "umap": 17.6098384857,
                "tsne": 73.2554092407,
                "pca": 67.0480898551
            },
            "y": {
                "umap": 20.6552314758,
                "tsne": 84.8935317993,
                "pca": 19.9517924871
            }
        },
        {
            "party": "fdp",
            "year": 1972,
            "size": 8.36,
            "fontSize": 12,
            "x": {
                "umap": 48.8803977966,
                "tsne": 62.7087173462,
                "pca": 81.554820812
            },
            "y": {
                "umap": 85.9776992798,
                "tsne": 0.0,
                "pca": 32.4022393845
            }
        },
        {
            "party": "spd",
            "year": 1972,
            "size": 45.85,
            "fontSize": 12,
            "x": {
                "umap": 17.8520526886,
                "tsne": 72.5073318481,
                "pca": 57.3359419218
            },
            "y": {
                "umap": 43.2322692871,
                "tsne": 46.1728172302,
                "pca": 23.3210974771
            }
        },
        {
            "party": "union",
            "year": 1976,
            "size": 48.63,
            "fontSize": 12,
            "x": {
                "umap": 27.9308414459,
                "tsne": 82.5131607056,
                "pca": 58.1193451365
            },
            "y": {
                "umap": 63.2715835571,
                "tsne": 82.8981552124,
                "pca": 6.9606099273
            }
        },
        {
            "party": "fdp",
            "year": 1976,
            "size": 7.92,
            "fontSize": 12,
            "x": {
                "umap": 46.7746543884,
                "tsne": 64.3897628784,
                "pca": 53.6315046343
            },
            "y": {
                "umap": 76.3319396973,
                "tsne": 9.8436288834,
                "pca": 21.8484338508
            }
        },
        {
            "party": "spd",
            "year": 1976,
            "size": 42.56,
            "fontSize": 12,
            "x": {
                "umap": 23.7997074127,
                "tsne": 72.5001220703,
                "pca": 57.1450531231
            },
            "y": {
                "umap": 41.7584953308,
                "tsne": 56.8052177429,
                "pca": 13.4025943938
            }
        },
        {
            "party": "union",
            "year": 1980,
            "size": 44.54,
            "fontSize": 12,
            "x": {
                "umap": 30.4016895294,
                "tsne": 77.6452484131,
                "pca": 61.0869606485
            },
            "y": {
                "umap": 57.7496299744,
                "tsne": 75.8893280029,
                "pca": 9.6765318131
            }
        },
        {
            "party": "fdp",
            "year": 1980,
            "size": 10.62,
            "fontSize": 12,
            "x": {
                "umap": 46.9542045593,
                "tsne": 70.6167373657,
                "pca": 43.048715299
            },
            "y": {
                "umap": 67.5027694702,
                "tsne": 14.7206230164,
                "pca": 23.8903076614
            }
        },
        {
            "party": "spd",
            "year": 1980,
            "size": 42.86,
            "fontSize": 12,
            "x": {
                "umap": 29.1752815247,
                "tsne": 67.5444030762,
                "pca": 51.2255176398
            },
            "y": {
                "umap": 35.7138900757,
                "tsne": 63.1268196106,
                "pca": 20.8703987491
            }
        },
        {
            "party": "union",
            "year": 1983,
            "size": 48.79,
            "fontSize": 12,
            "x": {
                "umap": 25.0971431732,
                "tsne": 72.1922225952,
                "pca": 63.8595847265
            },
            "y": {
                "umap": 54.1561851501,
                "tsne": 72.7768936157,
                "pca": 11.6201330849
            }
        },
        {
            "party": "fdp",
            "year": 1983,
            "size": 6.95,
            "fontSize": 12,
            "x": {
                "umap": 53.6814689636,
                "tsne": 66.5560455322,
                "pca": 53.6824079915
            },
            "y": {
                "umap": 72.9615631104,
                "tsne": 8.0652732849,
                "pca": 26.6171357806
            }
        },
        {
            "party": "gruene",
            "year": 1983,
            "size": 5.57,
            "fontSize": 12,
            "x": {
                "umap": 100.0,
                "tsne": 22.2864971161,
                "pca": 70.3716884496
            },
            "y": {
                "umap": 35.4537887573,
                "tsne": 24.1222381592,
                "pca": 70.039895282
            }
        },
        {
            "party": "spd",
            "year": 1983,
            "size": 38.18,
            "fontSize": 12,
            "x": {
                "umap": 29.3048381805,
                "tsne": 64.099395752,
                "pca": 55.8520450594
            },
            "y": {
                "umap": 43.9481048584,
                "tsne": 59.9840164185,
                "pca": 27.0139487859
            }
        },
        {
            "party": "union",
            "year": 1987,
            "size": 44.26,
            "fontSize": 12,
            "x": {
                "umap": 32.7856750488,
                "tsne": 62.7164001465,
                "pca": 48.5265425267
            },
            "y": {
                "umap": 25.2075519562,
                "tsne": 85.7833099365,
                "pca": 2.675823948
            }
        },
        {
            "party": "fdp",
            "year": 1987,
            "size": 9.09,
            "fontSize": 12,
            "x": {
                "umap": 59.4862060547,
                "tsne": 59.0664367676,
                "pca": 47.1721504272
            },
            "y": {
                "umap": 64.8798141479,
                "tsne": 7.3212957382,
                "pca": 29.6674219832
            }
        },
        {
            "party": "gruene",
            "year": 1987,
            "size": 8.26,
            "fontSize": 12,
            "x": {
                "umap": 98.1470794678,
                "tsne": 23.8456916809,
                "pca": 54.0098510958
            },
            "y": {
                "umap": 46.0117340088,
                "tsne": 26.4985237122,
                "pca": 96.5894564079
            }
        },
        {
            "party": "spd",
            "year": 1987,
            "size": 37.04,
            "fontSize": 12,
            "x": {
                "umap": 35.6945991516,
                "tsne": 61.4636497498,
                "pca": 48.6824278827
            },
            "y": {
                "umap": 46.7833480835,
                "tsne": 51.8708534241,
                "pca": 30.3430075747
            }
        },
        {
            "party": "union",
            "year": 1990,
            "size": 43.82,
            "fontSize": 12,
            "x": {
                "umap": 38.7583198547,
                "tsne": 53.1135025024,
                "pca": 43.690003237
            },
            "y": {
                "umap": 33.7383346558,
                "tsne": 85.85912323,
                "pca": 7.3597318969
            }
        },
        {
            "party": "fdp",
            "year": 1990,
            "size": 11.03,
            "fontSize": 12,
            "x": {
                "umap": 51.9492263794,
                "tsne": 56.1042251587,
                "pca": 38.7664018608
            },
            "y": {
                "umap": 63.2871856689,
                "tsne": 11.092168808,
                "pca": 25.3271791252
            }
        },
        {
            "party": "gruene",
            "year": 1990,
            "size": 5.05,
            "fontSize": 12,
            "x": {
                "umap": 93.7053756714,
                "tsne": 21.3868484497,
                "pca": 48.1391079265
            },
            "y": {
                "umap": 43.5545463562,
                "tsne": 30.5561218262,
                "pca": 100.0
            }
        },
        {
            "party": "linke",
            "year": 1990,
            "size": 2.43,
            "fontSize": 12,
            "x": {
                "umap": 87.5703659058,
                "tsne": 4.3841962814,
                "pca": 57.5176059036
            },
            "y": {
                "umap": 69.8039398193,
                "tsne": 34.4679145813,
                "pca": 99.2300283997
            }
        },
        {
            "party": "spd",
            "year": 1990,
            "size": 33.46,
            "fontSize": 12,
            "x": {
                "umap": 74.4419250488,
                "tsne": 38.6891288757,
                "pca": 43.1287125395
            },
            "y": {
                "umap": 26.9425449371,
                "tsne": 62.1589584351,
                "pca": 41.4032199523
            }
        },
        {
            "party": "union",
            "year": 1994,
            "size": 41.43,
            "fontSize": 12,
            "x": {
                "umap": 36.3307800293,
                "tsne": 53.9883918762,
                "pca": 41.9284954892
            },
            "y": {
                "umap": 18.3911972046,
                "tsne": 97.1248626709,
                "pca": 0.0
            }
        },
        {
            "party": "fdp",
            "year": 1994,
            "size": 6.92,
            "fontSize": 12,
            "x": {
                "umap": 49.475276947,
                "tsne": 52.8920059204,
                "pca": 23.3508331246
            },
            "y": {
                "umap": 55.8203697205,
                "tsne": 16.573381424,
                "pca": 23.2618440645
            }
        },
        {
            "party": "gruene",
            "year": 1994,
            "size": 7.27,
            "fontSize": 12,
            "x": {
                "umap": 85.8418502808,
                "tsne": 24.6217689514,
                "pca": 33.7705775263
            },
            "y": {
                "umap": 38.9021263123,
                "tsne": 35.3405761719,
                "pca": 89.1626619545
            }
        },
        {
            "party": "linke",
            "year": 1994,
            "size": 4.39,
            "fontSize": 12,
            "x": {
                "umap": 74.1140365601,
                "tsne": 0.0,
                "pca": 47.5080978208
            },
            "y": {
                "umap": 64.6812362671,
                "tsne": 38.5450553894,
                "pca": 91.7118136387
            }
        },
        {
            "party": "spd",
            "year": 1994,
            "size": 36.39,
            "fontSize": 12,
            "x": {
                "umap": 65.5667572021,
                "tsne": 40.844543457,
                "pca": 25.4911097514
            },
            "y": {
                "umap": 27.6430854797,
                "tsne": 52.4931602478,
                "pca": 36.0348572271
            }
        },
        {
            "party": "union",
            "year": 1998,
            "size": 35.14,
            "fontSize": 12,
            "x": {
                "umap": 40.9782447815,
                "tsne": 47.6606445312,
                "pca": 37.4554467879
            },
            "y": {
                "umap": 11.8495922089,
                "tsne": 96.5935440063,
                "pca": 4.4278586717
            }
        },
        {
            "party": "fdp",
            "year": 1998,
            "size": 6.25,
            "fontSize": 12,
            "x": {
                "umap": 54.9709396362,
                "tsne": 50.5353088379,
                "pca": 22.6114356021
            },
            "y": {
                "umap": 54.5491943359,
                "tsne": 18.3462715149,
                "pca": 19.3044302193
            }
        },
        {
            "party": "gruene",
            "year": 1998,
            "size": 6.7,
            "fontSize": 12,
            "x": {
                "umap": 86.4221038818,
                "tsne": 25.8533706665,
                "pca": 36.3487443511
            },
            "y": {
                "umap": 32.8632125854,
                "tsne": 40.3378791809,
                "pca": 87.8533281673
            }
        },
        {
            "party": "linke",
            "year": 1998,
            "size": 5.1,
            "fontSize": 12,
            "x": {
                "umap": 79.8840560913,
                "tsne": 0.3805978596,
                "pca": 45.3755203177
            },
            "y": {
                "umap": 61.4950256348,
                "tsne": 43.8567123413,
                "pca": 92.7589770293
            }
        },
        {
            "party": "spd",
            "year": 1998,
            "size": 40.93,
            "fontSize": 12,
            "x": {
                "umap": 61.9091033936,
                "tsne": 44.8629837036,
                "pca": 30.7531120213
            },
            "y": {
                "umap": 19.7277431488,
                "tsne": 58.7756767273,
                "pca": 24.9083770769
            }
        },
        {
            "party": "union",
            "year": 2002,
            "size": 38.51,
            "fontSize": 12,
            "x": {
                "umap": 47.0697631836,
                "tsne": 49.3033866882,
                "pca": 20.704828573
            },
            "y": {
                "umap": 19.5463638306,
                "tsne": 79.7996139526,
                "pca": 7.4599837281
            }
        },
        {
            "party": "fdp",
            "year": 2002,
            "size": 7.37,
            "fontSize": 12,
            "x": {
                "umap": 73.2610473633,
                "tsne": 57.979888916,
                "pca": 28.6079579566
            },
            "y": {
                "umap": 6.3512234688,
                "tsne": 30.346944809,
                "pca": 25.4501194541
            }
        },
        {
            "party": "gruene",
            "year": 2002,
            "size": 8.56,
            "fontSize": 12,
            "x": {
                "umap": 76.2009048462,
                "tsne": 12.2209358215,
                "pca": 9.209027108
            },
            "y": {
                "umap": 40.7053260803,
                "tsne": 62.7206573486,
                "pca": 60.4218400855
            }
        },
        {
            "party": "linke",
            "year": 2002,
            "size": 3.99,
            "fontSize": 12,
            "x": {
                "umap": 77.4040908813,
                "tsne": 3.4880671501,
                "pca": 30.6256489412
            },
            "y": {
                "umap": 56.1334152222,
                "tsne": 51.8105278015,
                "pca": 73.8771712392
            }
        },
        {
            "party": "spd",
            "year": 2002,
            "size": 38.52,
            "fontSize": 12,
            "x": {
                "umap": 50.6513786316,
                "tsne": 42.1776161194,
                "pca": 11.2912753906
            },
            "y": {
                "umap": 42.7694168091,
                "tsne": 68.1637496948,
                "pca": 15.7425051537
            }
        },
        {
            "party": "union",
            "year": 2005,
            "size": 35.17,
            "fontSize": 12,
            "x": {
                "umap": 53.0696754456,
                "tsne": 37.1136131287,
                "pca": 25.1618296949
            },
            "y": {
                "umap": 14.7052869797,
                "tsne": 86.3760147095,
                "pca": 13.7743650271
            }
        },
        {
            "party": "fdp",
            "year": 2005,
            "size": 9.83,
            "fontSize": 12,
            "x": {
                "umap": 70.2949371338,
                "tsne": 52.6834030151,
                "pca": 24.3137786472
            },
            "y": {
                "umap": 13.6001214981,
                "tsne": 25.7901515961,
                "pca": 21.4796824203
            }
        },
        {
            "party": "gruene",
            "year": 2005,
            "size": 8.12,
            "fontSize": 12,
            "x": {
                "umap": 70.4540176392,
                "tsne": 19.3320446014,
                "pca": 5.4584191256
            },
            "y": {
                "umap": 45.380771637,
                "tsne": 64.4794158936,
                "pca": 46.3810540222
            }
        },
        {
            "party": "linke",
            "year": 2005,
            "size": 8.71,
            "fontSize": 12,
            "x": {
                "umap": 84.2391281128,
                "tsne": 4.9236297607,
                "pca": 33.2974334285
            },
            "y": {
                "umap": 53.9722442627,
                "tsne": 50.654964447,
                "pca": 73.1211411839
            }
        },
        {
            "party": "spd",
            "year": 2005,
            "size": 34.25,
            "fontSize": 12,
            "x": {
                "umap": 44.498840332,
                "tsne": 39.6279411316,
                "pca": 19.6163844579
            },
            "y": {
                "umap": 41.7063713074,
                "tsne": 73.6598587036,
                "pca": 16.2712066495
            }
        },
        {
            "party": "union",
            "year": 2009,
            "size": 33.8,
            "fontSize": 12,
            "x": {
                "umap": 43.2351531982,
                "tsne": 46.4901046753,
                "pca": 15.1480954129
            },
            "y": {
                "umap": 26.1259651184,
                "tsne": 88.7299041748,
                "pca": 0.2721276146
            }
        },
        {
            "party": "fdp",
            "year": 2009,
            "size": 14.56,
            "fontSize": 12,
            "x": {
                "umap": 76.3239059448,
                "tsne": 56.2195129395,
                "pca": 24.3552385154
            },
            "y": {
                "umap": 11.9441461563,
                "tsne": 31.8229980469,
                "pca": 23.046084612
            }
        },
        {
            "party": "gruene",
            "year": 2009,
            "size": 10.71,
            "fontSize": 12,
            "x": {
                "umap": 64.5580444336,
                "tsne": 19.7574253082,
                "pca": 4.6056002444
            },
            "y": {
                "umap": 49.0530128479,
                "tsne": 58.3699951172,
                "pca": 51.8155506093
            }
        },
        {
            "party": "linke",
            "year": 2009,
            "size": 11.89,
            "fontSize": 12,
            "x": {
                "umap": 82.5344848633,
                "tsne": 12.4385375977,
                "pca": 24.8071581666
            },
            "y": {
                "umap": 82.3739013672,
                "tsne": 38.0479927063,
                "pca": 79.7829745821
            }
        },
        {
            "party": "spd",
            "year": 2009,
            "size": 23.03,
            "fontSize": 12,
            "x": {
                "umap": 57.3338317871,
                "tsne": 33.6326065063,
                "pca": 6.6241204942
            },
            "y": {
                "umap": 42.849609375,
                "tsne": 69.7287139893,
                "pca": 28.0586009739
            }
        },
        {
            "party": "afd",
            "year": 2013,
            "size": 4.7,
            "fontSize": 12,
            "x": {
                "umap": 64.7846908569,
                "tsne": 43.1522331238,
                "pca": 69.7260584046
            },
            "y": {
                "umap": 81.3414459229,
                "tsne": 23.7700119019,
                "pca": 56.6382311095
            }
        },
        {
            "party": "union",
            "year": 2013,
            "size": 41.55,
            "fontSize": 12,
            "x": {
                "umap": 50.4147109985,
                "tsne": 38.1436347961,
                "pca": 13.0932187991
            },
            "y": {
                "umap": 27.0726890564,
                "tsne": 89.6429519653,
                "pca": 3.3433929121
            }
        },
        {
            "party": "fdp",
            "year": 2013,
            "size": 4.76,
            "fontSize": 12,
            "x": {
                "umap": 56.0227050781,
                "tsne": 42.2428627014,
                "pca": 13.593673216
            },
            "y": {
                "umap": 26.4628105164,
                "tsne": 37.8572006226,
                "pca": 14.2401334209
            }
        },
        {
            "party": "gruene",
            "year": 2013,
            "size": 8.44,
            "fontSize": 12,
            "x": {
                "umap": 64.0374603271,
                "tsne": 25.6933364868,
                "pca": 0.0
            },
            "y": {
                "umap": 41.7568092346,
                "tsne": 56.9714355469,
                "pca": 48.9344034999
            }
        },
        {
            "party": "linke",
            "year": 2013,
            "size": 8.59,
            "fontSize": 12,
            "x": {
                "umap": 80.909576416,
                "tsne": 9.8817434311,
                "pca": 20.723359246
            },
            "y": {
                "umap": 75.5361175537,
                "tsne": 38.3013381958,
                "pca": 81.7908659252
            }
        },
        {
            "party": "spd",
            "year": 2013,
            "size": 25.74,
            "fontSize": 12,
            "x": {
                "umap": 54.4515686035,
                "tsne": 43.9684753418,
                "pca": 3.8486744724
            },
            "y": {
                "umap": 36.1610717773,
                "tsne": 52.3025093079,
                "pca": 26.9430260821
            }
        },
        {
            "party": "afd",
            "year": 2017,
            "size": 12.64,
            "fontSize": 12,
            "x": {
                "umap": 60.4373283386,
                "tsne": 49.3367271423,
                "pca": 57.4388680972
            },
            "y": {
                "umap": 3.1468062401,
                "tsne": 66.2705459595,
                "pca": 43.7567184198
            }
        },
        {
            "party": "union",
            "year": 2017,
            "size": 32.93,
            "fontSize": 12,
            "x": {
                "umap": 46.8777961731,
                "tsne": 43.2538642883,
                "pca": 17.491011921
            },
            "y": {
                "umap": 32.8940620422,
                "tsne": 84.6860427856,
                "pca": 4.0476009747
            }
        },
        {
            "party": "fdp",
            "year": 2017,
            "size": 10.75,
            "fontSize": 12,
            "x": {
                "umap": 49.7636604309,
                "tsne": 34.1792030334,
                "pca": 37.4748174371
            },
            "y": {
                "umap": 0.5720114112,
                "tsne": 52.8005409241,
                "pca": 34.2678970417
            }
        },
        {
            "party": "gruene",
            "year": 2017,
            "size": 8.94,
            "fontSize": 12,
            "x": {
                "umap": 68.4523086548,
                "tsne": 24.3354415894,
                "pca": 11.9672650937
            },
            "y": {
                "umap": 36.4057731628,
                "tsne": 54.1366920471,
                "pca": 46.7625930243
            }
        },
        {
            "party": "linke",
            "year": 2017,
            "size": 9.24,
            "fontSize": 12,
            "x": {
                "umap": 76.1678085327,
                "tsne": 11.5090456009,
                "pca": 16.9764264867
            },
            "y": {
                "umap": 78.0497894287,
                "tsne": 43.78748703,
                "pca": 78.6957425109
            }
        },
        {
            "party": "spd",
            "year": 2017,
            "size": 20.51,
            "fontSize": 12,
            "x": {
                "umap": 59.9168968201,
                "tsne": 28.5736026764,
                "pca": 2.5771969969
            },
            "y": {
                "umap": 34.5228767395,
                "tsne": 65.0618667603,
                "pca": 26.0924519715
            }
        }
    ]
}